inflationpy/__init__.py
inflationpy/py.typed
inflationpy/version.txt
inflationpy/core/__init__.py
inflationpy/core/functions.py
inflationpy/core/model.py
inflationpy/data/__init__.py
inflationpy/data/data.py
inflationpy/data/sigma1.dat
inflationpy/data/sigma2.dat
inflationpy/solver/__init__.py
inflationpy/solver/function_solver.py
inflationpy/solver/inflation_solvers.py
inflationpy/solver/misc_solver.py
inflationpy-0.9.0.dist-info/LICENSE
inflationpy-0.9.0.dist-info/METADATA
inflationpy-0.9.0.dist-info/WHEEL
inflationpy-0.9.0.dist-info/top_level.txt
inflationpy-0.9.0.dist-info/RECORD
